lattpy/__init__.py
lattpy/_version.py
lattpy/atom.py
lattpy/basis.py
lattpy/data.py
lattpy/disptools.py
lattpy/lattice.py
lattpy/plotting.py
lattpy/shape.py
lattpy/spatial.py
lattpy/structure.py
lattpy/utils.py
lattpy/tests/__init__.py
lattpy/tests/test_atom.py
lattpy/tests/test_basis.py
lattpy/tests/test_data.py
lattpy/tests/test_lattice.py
lattpy/tests/test_shape.py
lattpy/tests/test_spatial.py
lattpy/tests/test_structure.py
lattpy/tests/test_utils.py
lattpy-0.7.7.dist-info/LICENSE
lattpy-0.7.7.dist-info/METADATA
lattpy-0.7.7.dist-info/WHEEL
lattpy-0.7.7.dist-info/top_level.txt
lattpy-0.7.7.dist-info/RECORD
