Metadata-Version: 2.1
Name: lattpy
Version: 0.7.7
Summary: Simple and efficient Python package for modeling d-dimensional Bravais lattices in solid state physics.
Home-page: https://github.com/dylanljones/lattpy
Author: Dylan Jones
Author-email: dylanljones94@gmail.com
License: MIT
Project-URL: Source, https://github.com/dylanljones/lattpy
Project-URL: Documentation, https://lattpy.readthedocs.io/
Project-URL: Tracker, https://github.com/dylanljones/lattpy/issues
Classifier: Development Status :: 3 - Alpha
Classifier: Intended Audience :: Science/Research
Classifier: Topic :: Scientific/Engineering :: Physics
Classifier: Natural Language :: English
Classifier: License :: OSI Approved :: MIT License
Classifier: Programming Language :: Python :: 3
Classifier: Programming Language :: Python :: 3 :: Only
Classifier: Programming Language :: Python :: 3.7
Classifier: Programming Language :: Python :: 3.8
Classifier: Programming Language :: Python :: 3.9
Classifier: Programming Language :: Python :: 3.10
Classifier: Programming Language :: Python :: 3.11
Requires-Python: >=3.7
License-File: LICENSE
Requires-Dist: setuptools (>=60.0.0)
Requires-Dist: setuptools-scm[toml] (>=4)
Requires-Dist: numpy (>=1.20.3)
Requires-Dist: scipy (>=1.7.1)
Requires-Dist: matplotlib (>=3.0.0)
Requires-Dist: pytest (>=6.2.5)
Requires-Dist: hypothesis (>=6.0.0)
Requires-Dist: colorcet (>=2.0.0)
Provides-Extra: build
Requires-Dist: wheel (>=0.37.0) ; extra == 'build'
Provides-Extra: test
Requires-Dist: pytest-cov ; extra == 'test'
